academia/__init__.py
academia/agents/__init__.py
academia/agents/dqn_agent.py
academia/agents/ppo_agent.py
academia/agents/ql_agent.py
academia/agents/sarsa_agent.py
academia/agents/base/__init__.py
academia/agents/base/agent.py
academia/agents/base/epsilon_greedy_agent.py
academia/agents/base/tabular_agent.py
academia/curriculum/__init__.py
academia/curriculum/config_loaders.py
academia/curriculum/curriculum.py
academia/curriculum/learning_task.py
academia/environments/__init__.py
academia/environments/bridge_building.py
academia/environments/door_key.py
academia/environments/lava_crossing.py
academia/environments/lunar_lander.py
academia/environments/ms_pacman.py
academia/environments/base/__init__.py
academia/environments/base/generic_atari_wrapper.py
academia/environments/base/generic_gymnasium_wrapper.py
academia/environments/base/generic_minigrid_wrapper.py
academia/environments/base/scalable_env.py
academia/tools/__init__.py
academia/tools/agent_debugger.py
academia/tools/visualizations.py
academia/utils/__init__.py
academia/utils/saving_loading.py
academia/utils/stopwatch.py
academia/utils/models/__init__.py
academia/utils/models/bridge_building.py
academia/utils/models/door_key.py
academia/utils/models/lava_crossing.py
academia/utils/models/lunar_lander.py
academia/utils/models/ms_pacman.py
academia_rl-0.2.0.dist-info/METADATA
academia_rl-0.2.0.dist-info/WHEEL
academia_rl-0.2.0.dist-info/licenses/LICENSE
academia_rl-0.2.0.dist-info/RECORD
