Metadata-Version: 2.3
Name: academia-rl
Version: 0.2.0
Summary: Easy-to-use tools for Curriculum Learning
Project-URL: Source code, https://github.com/krezelj/academia
Project-URL: Documentation, https://academia.readthedocs.io/
Author-email: krezelj <jasiekk9@gmail.com>, guts <szymon.gut01@gmail.com>, maciejors <maciej.orslowski@gmail.com>
License-File: LICENSE
Keywords: curriculum-learning,reinforcement-learning
Classifier: Development Status :: 4 - Beta
Classifier: Intended Audience :: Science/Research
Classifier: License :: OSI Approved :: MIT License
Classifier: Operating System :: OS Independent
Classifier: Programming Language :: Python :: 3
Classifier: Programming Language :: Python :: 3.9
Classifier: Programming Language :: Python :: 3.10
Classifier: Programming Language :: Python :: 3.11
Classifier: Programming Language :: Python :: 3.12
Classifier: Topic :: Scientific/Engineering :: Artificial Intelligence
Requires-Python: >=3.9
Requires-Dist: gymnasium~=0.29
Requires-Dist: kaleido~=0.2
Requires-Dist: numpy~=1.25
Requires-Dist: plotly~=5.18
Requires-Dist: pytimedinput~=2.0
Requires-Dist: pyyaml~=6.0
Requires-Dist: torch~=2.1
